{
  "name": "TART Cargo Development",
  "image": "mcr.microsoft.com/devcontainers/python:3.12-bookworm",
  
  "features": {
    "ghcr.io/devcontainers/features/common-utils:2": {
      "installZsh": true,
      "installOhMyZsh": true,
      "upgradePackages": true
    }
  },

  "postCreateCommand": "bash .devcontainer/post-create.sh",
  
  "customizations": {
    "vscode": {
      "extensions": [
        "ms-python.python",
        "ms-python.vscode-pylance"
      ],
      "settings": {
        "python.defaultInterpreterPath": "/usr/local/bin/python",
        "python.linting.enabled": true,
        "python.linting.pylintEnabled": false,
        "python.formatting.autopep8Path": "/usr/local/py-utils/bin/autopep8",
        "python.formatting.blackPath": "/usr/local/py-utils/bin/black",
        "python.formatting.yapfPath": "/usr/local/py-utils/bin/yapf",
        "python.linting.banditPath": "/usr/local/py-utils/bin/bandit",
        "python.linting.flake8Path": "/usr/local/py-utils/bin/flake8",
        "python.linting.mypyPath": "/usr/local/py-utils/bin/mypy",
        "python.linting.pycodestylePath": "/usr/local/py-utils/bin/pycodestyle",
        "python.linting.pydocstylePath": "/usr/local/py-utils/bin/pydocstyle",
        "python.linting.pylintPath": "/usr/local/py-utils/bin/pylint"
      }
    }
  },

  "remoteUser": "vscode",
  
  "mounts": [
    "source=/var/run/docker.sock,target=/var/run/docker.sock,type=bind"
  ],
  
  "runArgs": [
    "--privileged"
  ]
}
